modulesbuilder/__init__.py
modulesbuilder/build.py
modulesbuilder/module.py
modulesbuilder/modules.py
modulesbuilder/version.py
modulesbuilder-1.1.1.dist-info/LICENSE.txt
modulesbuilder-1.1.1.dist-info/METADATA
modulesbuilder-1.1.1.dist-info/WHEEL
modulesbuilder-1.1.1.dist-info/top_level.txt
modulesbuilder-1.1.1.dist-info/RECORD
