Metadata-Version: 2.1
Name: modulesbuilder
Version: 1.1.1
Summary: Build tools for Environment Modules
Home-page: https://github.com/andbanman/modulesbuilder
Author: Andrew Banman
Author-email: abanman@pnri.org
License: UNKNOWN
Project-URL: Bug Tracker, https://github.com/andbanman/modulesbuilder/issues
Platform: UNKNOWN
Classifier: Programming Language :: Python :: 3
Classifier: License :: OSI Approved :: MIT License
License-File: LICENSE.txt
Requires-Dist: colorama
Requires-Dist: docker
